<?xml version="1.0" encoding="UTF-8"?>
<feature
      id="org.eclipse.datatools.enablement.sap.feature"
      label="%featureName"
      version="1.9.2.v201109161655-540AkF7AJ7YEJBU7S"
      provider-name="%providerName"
      plugin="org.eclipse.datatools.enablement.finfo"
      image="eclipse_update_120.jpg">

   <description>
      %description
   </description>

   <copyright>
      %featureCopyright
   </copyright>

   <license url="%licenseURL">
      %license
   </license>

   <url>
      <update label="%updateSiteName" url="http://download.eclipse.org/datatools/updates"/>
      <discovery label="%updateSiteName" url="http://download.eclipse.org/datatools/updates"/>
   </url>

   <requires>
      <import feature="org.eclipse.datatools.modelbase.feature" version="1.8.0" match="greaterOrEqual"/>
      <import feature="org.eclipse.datatools.connectivity.feature" version="1.8.0" match="greaterOrEqual"/>
      <import feature="org.eclipse.datatools.connectivity.oda.feature" version="1.8.0" match="greaterOrEqual"/>
      <import feature="org.eclipse.datatools.connectivity.oda.designer.feature" version="1.8.0" match="greaterOrEqual"/>
      <import feature="org.eclipse.datatools.sqldevtools.feature" version="1.8.0" match="greaterOrEqual"/>
      <import feature="org.eclipse.datatools.enablement.jdbc.feature" version="1.8.0" match="greaterOrEqual"/>
   </requires>

   <plugin
         id="org.eclipse.datatools.enablement.sap.maxdb.dbdefinition"
         download-size="0"
         install-size="0"
         version="1.0.0.v201107221507"
         unpack="false"/>

   <plugin
         id="org.eclipse.datatools.enablement.sap.maxdb"
         download-size="0"
         install-size="0"
         version="1.0.0.v201107221507"
         unpack="false"/>

   <plugin
         id="org.eclipse.datatools.enablement.sap.maxdb.ui"
         download-size="0"
         install-size="0"
         version="1.0.0.v201107221507"
         unpack="false"/>

   <plugin
         id="org.eclipse.datatools.enablement.finfo"
         download-size="0"
         install-size="0"
         version="1.5.1.v200906161800"
         unpack="false"/>

</feature>
